sendmail/__init__.py
sendmail/apps.py
sendmail/backends.py
sendmail/cache.py
sendmail/cache_utils.py
sendmail/checks.py
sendmail/config.py
sendmail/connections.py
sendmail/dblock.py
sendmail/django_compressor.py
sendmail/logutils.py
sendmail/mail.py
sendmail/mixins.py
sendmail/parser.py
sendmail/sanitizer.py
sendmail/settings.py
sendmail/signals.py
sendmail/tasks.py
sendmail/test_urls.py
sendmail/urls.py
sendmail/utils.py
sendmail/validators.py
sendmail/version.txt
sendmail/views.py
sendmail/admin/__init__.py
sendmail/admin/admin_utils.py
sendmail/admin/attachment.py
sendmail/admin/emailaddress.py
sendmail/admin/emailmerge.py
sendmail/admin/emailmodel.py
sendmail/admin/log.py
sendmail/admin/newsletter.py
sendmail/admin/placeholder.py
sendmail/locale/de/LC_MESSAGES/django.mo
sendmail/locale/de/LC_MESSAGES/django.po
sendmail/locale/es/LC_MESSAGES/django.mo
sendmail/locale/es/LC_MESSAGES/django.po
sendmail/locale/it/LC_MESSAGES/django.mo
sendmail/locale/it/LC_MESSAGES/django.po
sendmail/locale/pl/LC_MESSAGES/django.mo
sendmail/locale/pl/LC_MESSAGES/django.po
sendmail/locale/ru/LC_MESSAGES/django.mo
sendmail/locale/ru/LC_MESSAGES/django.po
sendmail/locale/uk/LC_MESSAGES/django.mo
sendmail/locale/uk/LC_MESSAGES/django.po
sendmail/management/__init__.py
sendmail/management/commands/__init__.py
sendmail/management/commands/sendmail.py
sendmail/management/commands/subcommands/__init__.py
sendmail/management/commands/subcommands/base.py
sendmail/management/commands/subcommands/cleanup_mail.py
sendmail/management/commands/subcommands/dblocks.py
sendmail/management/commands/subcommands/send_queued_mail.py
sendmail/migrations/0001_initial.py
sendmail/migrations/0002_emailmergecontentmodel_and_more.py
sendmail/migrations/0003_alter_placeholdercontent_language.py
sendmail/migrations/0004_emailmergecontentmodel_extra_attachments_and_more.py
sendmail/migrations/0005_alter_attachment_emails_and_more.py
sendmail/migrations/0006_alter_attachment_file.py
django_sendmail-4.0.dist-info/AUTHORS.rst
django_sendmail-4.0.dist-info/LICENSE.txt
django_sendmail-4.0.dist-info/METADATA
django_sendmail-4.0.dist-info/WHEEL
django_sendmail-4.0.dist-info/top_level.txt
django_sendmail-4.0.dist-info/RECORD
