Metadata-Version: 2.1
Name: django-sendmail
Version: 4.0
Summary: A Django app to monitor and send mail asynchronously, complete with template support.
Home-page: https://github.com/jrief/django-sendmail
Author: Mykhailo Poienko, Jacob Rief
Author-email: 22IMC10258@fh-krems.ac.at
License: MIT
Project-URL: Documentation, https://django-sendmail.readthedocs.io/en/latest/
Project-URL: Source, https://github.com/jrief/django-sendmail
Keywords: django,email,sendmail,template,async,celery
Classifier: Development Status :: 5 - Production/Stable
Classifier: Environment :: Web Environment
Classifier: Framework :: Django
Classifier: Intended Audience :: Developers
Classifier: License :: OSI Approved :: MIT License
Classifier: Operating System :: OS Independent
Classifier: Programming Language :: Python
Classifier: Programming Language :: Python :: 3
Classifier: Programming Language :: Python :: 3 :: Only
Classifier: Programming Language :: Python :: 3.10
Classifier: Programming Language :: Python :: 3.11
Classifier: Programming Language :: Python :: 3.12
Classifier: Topic :: Communications :: Email
Classifier: Topic :: Internet :: WWW/HTTP
Classifier: Topic :: Software Development :: Libraries :: Python Modules
License-File: LICENSE.txt
License-File: AUTHORS.rst
Requires-Dist: Django>=4.0
Requires-Dist: django-ckeditor>=6.0
Requires-Dist: lxml>=5.0
Requires-Dist: nh3>=0.2
Provides-Extra: jsoneditor
Requires-Dist: django-jsoneditor>=0.2.0; extra == "jsoneditor"
